bookizer/__init__.py
bookizer/__main__.py
Bookizer-0.0.8.dist-info/LICENSE
Bookizer-0.0.8.dist-info/METADATA
Bookizer-0.0.8.dist-info/WHEEL
Bookizer-0.0.8.dist-info/entry_points.txt
Bookizer-0.0.8.dist-info/top_level.txt
Bookizer-0.0.8.dist-info/RECORD
