Metadata-Version: 2.1
Name: Bookizer
Version: 0.0.8
Summary: Bookizer get multiple CSV files and converts them into a big CSV/ODS/XLS/XLSX file.
Home-page: UNKNOWN
Author: Daniel Ripoll
Author-email: info@danielripoll.es
License: BSD
Project-URL: Code, https://github.com/JustDevZero/bookizer
Project-URL: Issue tracker, https://github.com/JustDevZero/bookizer
Keywords: csv,xls,xlsx,odf
Platform: Linux
Platform: macOS
Platform: Windows
Classifier: Development Status :: 5 - Production/Stable
Classifier: Intended Audience :: Developers
Classifier: Intended Audience :: System Administrators
Classifier: License :: OSI Approved :: BSD License
Classifier: Programming Language :: Python :: 3
Classifier: Programming Language :: Python :: 3.6
Classifier: Programming Language :: Python :: 3.7
Classifier: Programming Language :: Python :: 3.8
Classifier: Programming Language :: Python :: 3.9
Classifier: Topic :: Utilities
Classifier: Topic :: Text Processing
Classifier: Topic :: Text Processing :: Indexing
Requires-Python: >=3.6
Requires-Dist: odfpy (~=1.4.1)
Requires-Dist: openpyxl (~=3.0.9)
Requires-Dist: pandas (~=1.3.4)
Requires-Dist: xlwt (~=1.3.0)
